{
  "result": [
    {
      "Name": "Daniel Lorem Ipsum ",
      "Email": "daniel@loremipsum",
      "Cidade": "Rio de Janeiro"
    },
    {
      "Name": "Marco Lorem Ipsum",
      "Email": "marco@loremipsum",
      "Cidade": "Sao Paulo"
    },
    {
      "Name": "Julio Lorem Ipsum",
      "Email": "@loremipsum",
      "Cidade": "Santo André"
    },
    {
      "Name": "Joao Lorem Ipsum",
      "Email": "@loremipsum",
      "Cidade": "Altos"
    },
    {
      "Name": "Maria Lorem Ipsum",
      "Email": "maria@loremipsum",
      "Cidade": "Anguera"
    },
    {
      "Name": "Alexandra Lorem Ipsum",
      "Email": "alexandra@loremipsum",
      "Cidade": "Alvarães"
    },
    {
      "Name": "Diana Lorem Ipsum",
      "Email": "diana@loremipsum",
      "Cidade": "Teresina"
    },
    {
      "Name": "Mariana Lorem Ipsum",
      "Email": "mari@loremipsum",
      "Cidade": "Blumenau"
    }
  ]
}
